endoreg_db_api/Secure_Requests.md
endoreg_db_api/TODO.md
endoreg_db_api/__init__.py
endoreg_db_api/asgi.py
endoreg_db_api/settings_base.py
endoreg_db_api/urls.py
endoreg_db_api/views.py
endoreg_db_api/wsgi.py
endoreg_db_api/api/urls.py
endoreg_db_api/api/views.py
endoreg_db_api/settings_dev/__init__.py
endoreg_db_api/settings_prod/__init__.py
endoreg_db_api/utils/__init__.py
endoreg_db_api-0.1.2.dist-info/METADATA
endoreg_db_api-0.1.2.dist-info/WHEEL
endoreg_db_api-0.1.2.dist-info/RECORD
